<?xml version="1.0" encoding="utf-8"?>
<SampleMetadata>
	<ID>93aa99cf-dc24-4149-84c6-7ad1143272e6</ID>
	<IsFullApplication>false</IsFullApplication>
    <Brief>Xamarin.Forms includes an Easing class that allows you to specify a transfer function that controls how animations speed up or slow down as they're running. This sample demonstrates how to consume the pre-defined easing functions, and how to create custom easing functions.</Brief>
	<Level>Beginner</Level>
	<LicenseRequirement>Indie</LicenseRequirement>
	<Tags>Animation, Xamarin.Forms</Tags>
	<SupportedPlatforms>Android, iOS, Windows</SupportedPlatforms>
	<Gallery>true</Gallery>
</SampleMetadata>
